visionPDF/__init__.py
visionPDF/visionPDF.py
visionPDF-1.0.1.dist-info/LICENSE
visionPDF-1.0.1.dist-info/METADATA
visionPDF-1.0.1.dist-info/WHEEL
visionPDF-1.0.1.dist-info/top_level.txt
visionPDF-1.0.1.dist-info/RECORD
