Metadata-Version: 2.1
Name: visionPDF
Version: 1.0.1
Summary: Modulo que ler,traduz e escreve arquivos PDF.
Home-page: https://github.com/informeai/vision
Author: Wellington Gadelha
Author-email: contato.informeai@gmail.com
License: UNKNOWN
Platform: UNKNOWN
Classifier: Programming Language :: Python :: 3
Classifier: License :: OSI Approved :: MIT License
Classifier: Operating System :: OS Independent
Requires-Python: >=3.6
Requires-Dist: PyPDF2
Requires-Dist: reportlab
Requires-Dist: karkipytranslator
